pawpyrus/__init__.py
pawpyrus/main.py
pawpyrus-2025.2.27.0.dist-info/METADATA
pawpyrus-2025.2.27.0.dist-info/WHEEL
pawpyrus-2025.2.27.0.dist-info/entry_points.txt
pawpyrus-2025.2.27.0.dist-info/licenses/LICENSE
pawpyrus-2025.2.27.0.dist-info/RECORD
