Metadata-Version: 2.4
Name: pawpyrus
Version: 2025.2.27.0
Summary: A minimalist paper data storage based on QR codes
Project-URL: Repository, https://codeberg.org/screwery/pawpyrus
Project-URL: Issues, https://codeberg.org/screwery/pawpyrus/issues
Project-URL: Changelog, https://codeberg.org/screwery/pawpyrus/src/branch/main/CHANGELOG.md
Author-email: Ellie Viesná <snowboard_refinery@proton.me>
License-Expression: GPL-3.0-or-later
License-File: LICENSE
Keywords: ArUco,QR,data storage,paper
Classifier: Development Status :: 4 - Beta
Classifier: Environment :: Console
Classifier: License :: OSI Approved :: GNU General Public License v3 (GPLv3)
Classifier: Natural Language :: English
Classifier: Operating System :: OS Independent
Classifier: Programming Language :: Python :: 3.12
Requires-Python: >=3.12
Requires-Dist: argparse
Requires-Dist: bitarray
Requires-Dist: more-itertools
Requires-Dist: numpy
Requires-Dist: opencv-contrib-python
Requires-Dist: opencv-python
Requires-Dist: pyzbar
Requires-Dist: qrcode
Requires-Dist: reportlab
Requires-Dist: svglib
Requires-Dist: tqdm
